{
  "name": "Roles",
  "fields": [
    {
      "fieldName": "role",
      "fieldType": "String",
      "fieldValidateRules": [
        "minlength",
        "required",
        "unique"
      ],
      "fieldValidateRulesMinlength": "1"
    }
  ],
  "relationships": [],
  "changelogDate": "20210410141642",
  "entityTableName": "roles",
  "dto": "no",
  "pagination": "no",
  "service": "no",
  "jpaMetamodelFiltering": false,
  "fluentMethods": true,
  "readOnly": false,
  "embedded": false,
  "clientRootFolder": "",
  "applications": "*"
}
